{
  "config": {
    "mapLabel": "Аудитории 1–5. Этаж 2",
    "mapName": "c3-cr-f2",
    "prevMap": "c3-cr-f1",
    "nextMap": "",
    "floorName": 2
  },
  "items": {
    "stairs": {
      "id": "stairs",
      "action": "move",
      "direction": "c3-cr-f1"
    },
    "stairs_2": {
      "id": "stairs_2",
      "action": "move",
      "direction": "c3-cr-f1"
    },
    "stairs_3": {
      "id": "stairs_3",
      "action": "move",
      "direction": "c3-cr-f1"
    },
    "transition": {
      "id": "transition",
      "action": "move",
      "direction": "c3-f2"
    },
    "transition_2": {
      "id": "transition_2",
      "action": "move",
      "direction": "c6-f1"
    },
    "c3-f1-n107_2": {
      "id": "c3-f1-n107_2",
      "name": "3-1 Ректорат Зал заседаний",
      "action": "info",
      "disc": "Ректорат. Зал заседаний учёного совета.",
      "additional": {
        "phone": "",
        "responsible": "",
        "workingHours": "",
        "email": "",
        "website": "",
        "timetable": ""
      }
    },
    "c3-f1-n107_3": {
      "id": "c3-f1-n107_3",
      "name": "3-2 Лекционная аудитория",
      "action": "info",
      "disc": "Лекционная аудитория.",
      "additional": {
        "phone": "",
        "responsible": "",
        "workingHours": "",
        "email": "",
        "website": "",
        "timetable": ""
      }
    },
    "c3-f1-n107": {
      "id": "c3-f1-n107",
      "name": "3-3 Лекционная аудитория",
      "action": "info",
      "disc": "Лекционная аудитория.",
      "additional": {
        "phone": "",
        "responsible": "",
        "workingHours": "",
        "email": "",
        "website": "",
        "timetable": ""
      }
    },
    "c3-f1-n131": {
      "id": "c3-f1-n131",
      "name": "3-4 Лекционная аудитория",
      "action": "info",
      "disc": "Лекционная аудитория.",
      "additional": {
        "phone": "",
        "responsible": "",
        "workingHours": "",
        "email": "",
        "website": "",
        "timetable": ""
      }
    },
    "c3-f1-n131_2": {
      "id": "c3-f1-n131_2",
      "name": "3-5 Лекционная аудитория",
      "action": "info",
      "disc": "Лекционная аудитория.",
      "additional": {
        "phone": "",
        "responsible": "",
        "workingHours": "",
        "email": "",
        "website": "",
        "timetable": ""
      }
    },
    "c3-f1-n131_4": {
      "id": "c3-f1-n131_4",
      "name": "Буфет «Халяль»",
      "action": "info",
      "disc": "Ассортимент: Халяльная выпечка, кондитерские изделия. Соки, лимонады, кофе (кофемашина).",
      "additional": {
        "phone": "",
        "responsible": "",
        "workingHours": "Во время учебного года, пн-пт с 08:00 по 16:00, сб выходной.",
        "email": "",
        "website": "",
        "timetable": ""
      }
    },
    "coffee": {
      "id": "coffee",
      "name": "Кофейный автомат 1",
      "action": "info",
      "disc": "",
      "additional": {
        "phone": "",
        "responsible": "",
        "workingHours": "",
        "email": "",
        "website": "",
        "timetable": ""
      }
    },
    "coffee_2": {
      "id": "coffee_2",
      "name": "Кофейный автомат 2",
      "action": "info",
      "disc": "",
      "additional": {
        "phone": "",
        "responsible": "",
        "workingHours": "",
        "email": "",
        "website": "",
        "timetable": ""
      }
    },
    "coffee_3": {
      "id": "coffee_3",
      "name": "Кофейный автомат 3",
      "action": "info",
      "disc": "",
      "additional": {
        "phone": "",
        "responsible": "",
        "workingHours": "",
        "email": "",
        "website": "",
        "timetable": ""
      }
    },
    "food": {
      "id": "food",
      "name": "Торговый автомат 1",
      "action": "info",
      "disc": "",
      "additional": {
        "phone": "",
        "responsible": "",
        "workingHours": "",
        "email": "",
        "website": "",
        "timetable": ""
      }
    },
    "food_2": {
      "id": "food_2",
      "name": "Торговый автомат 2",
      "action": "info",
      "disc": "",
      "additional": {
        "phone": "",
        "responsible": "",
        "workingHours": "",
        "email": "",
        "website": "",
        "timetable": ""
      }
    },
    "c3-f1-n131_3": {
      "id": "c3-f1-n131_3",
      "name": "Хоз. помещение",
      "action": "info",
      "disc": "",
      "additional": {
        "phone": "",
        "responsible": "",
        "workingHours": "",
        "email": "",
        "website": "",
        "timetable": ""
      }
    },
    "c3-f1-n131_5": {
      "id": "c3-f1-n131_5",
      "name": "Центр патриотич. воспитания УлГТУ",
      "action": "info",
      "disc": "",
      "additional": {
        "phone": "",
        "responsible": "",
        "workingHours": "",
        "email": "",
        "website": "",
        "timetable": ""
      }
    }
  }
}
